kid/__init__.py
kid/__main__.py
kid/util.py
kid_util-1.0.1.dist-info/LICENSE
kid_util-1.0.1.dist-info/METADATA
kid_util-1.0.1.dist-info/WHEEL
kid_util-1.0.1.dist-info/top_level.txt
kid_util-1.0.1.dist-info/RECORD
