Metadata-Version: 2.1
Name: kid-util
Version: 1.0.1
Summary: Module for making and verifying KID numbers
Home-page: https://github.com/Ondkloss/kid-util
Author: Halvor Holsten Strand
Author-email: halvor.holsten.strand@gmail.com
License: WTFPL
Platform: UNKNOWN
